{
  "nomeCorso": "Sistemi distribuiti",
  "docente": "Giorgio Gambosi, Giorgio Gambosi",
  "annoAccademico": "2004-2005",
  "crediti": "6",
  "settore": "",
  "anno": "1",
  "semestre": "1",
  "propedeuticit\u00e0": "Nessuna",
  "comunicazioni": [],
  "lezioni": [],
  "materiale": [],
  "programma": "Web services: caratteristiche generali. Gli standard SOAP, WSDL, UDDI. Sviluppo di servizi web: la piattaforma Axis. Problematiche ulteriori nello sviluppo di architetture service-oriented e relativi standard. Reti peer-to-peer:caratteristiche generali.",
  "testiRiferimento": "",
  "ricevimento": "",
  "modalit\u00e0Esame": "null"
}